[
  { "id": 1, "name": "Dior Sauvage", "category": "bestseller", "price": { "10g": 85000, "50g": 320000, "100g": 580000 }, "image": "https://parfumstock.uz/thumb/2/eBNXkH1T3xY0SHSSoiCEYg/r/d/3348901520065.jpg", "description": "Fresh and spicy fragrance with bergamot and ambroxan" },
  { "id": 2, "name": "Dior Sauvage Elixir", "category": "bestseller", "price": { "10g": 95000, "50g": 360000, "100g": 670000 }, "image": "https://avatars.mds.yandex.net/get-mpic/16488918/2a00000197e43ca35a53d5e77c97565f9fa3/orig", "description": "Intense concentration with nutmeg and cinnamon" },
  { "id": 3, "name": "Bleu de Chanel", "category": "bestseller", "price": { "10g": 88000, "50g": 330000, "100g": 600000 }, "image": "https://swissyarn.com/wp-content/uploads/2023/04/Chanel-Bleu-De-Parfum-PH-EDP-100ml-4.jpg", "description": "Citrus and woody aromatic fragrance" },
  { "id": 4, "name": "Chanel No.5", "category": "premium", "price": { "10g": 140000, "50g": 530000, "100g": 980000 }, "image": "https://avatars.mds.yandex.net/get-mpic/12591611/2a000001978723a8f9da7d09b7f4e691f742/orig", "description": "Iconic floral aldehyde with ylang ylang" },
  { "id": 5, "name": "Chanel Coco Mademoiselle", "category": "bestseller", "price": { "10g": 105000, "50g": 400000, "100g": 740000 }, "image": "https://ir.ozone.ru/s3/multimedia-u/c1000/6726558738.jpg", "description": "Orange and patchouli with rose" },
  { "id": 6, "name": "Chanel Chance", "category": "bestseller", "price": { "10g": 100000, "50g": 380000, "100g": 700000 }, "image": "https://parfumstock.uz/thumb/2/u6fFNXK9oVglX_g9GVtwsA/r/d/1590499-01.jpg", "description": "Pink pepper and jasmine with musk" },
  { "id": 7, "name": "Chanel Allure Homme", "category": "bestseller", "price": { "10g": 92000, "50g": 350000, "100g": 650000 }, "image": "https://parfumstock.uz/thumb/2/tPANjpYhrGV1-7GD4X8kag/r/d/504021214_50ml_hero.jpg", "description": "Fresh and spicy with citrus and woody notes" },
  { "id": 8, "name": "Creed Aventus", "category": "premium", "price": { "10g": 120000, "50g": 450000, "100g": 830000 }, "image": "https://images.uzum.uz/d0g8s3a7s4fo7mq8oms0/original.jpg", "description": "Pineapple and birch masterpiece" },
  { "id": 9, "name": "Creed Silver Mountain Water", "category": "premium", "price": { "10g": 115000, "50g": 435000, "100g": 800000 }, "image": "https://perfumer.uz/image/cache/catalog/%D0%A3%D0%BD%D0%B8%D1%81%D0%B5%D0%BA%D1%81%202024/Silver%20Mountain%20Water%20Creed-1000x1000.jpg", "description": "Fresh aquatic with green tea and blackcurrant" },
  { "id": 10, "name": "Baccarat Rouge 540", "category": "premium", "price": { "10g": 150000, "50g": 570000, "100g": 1050000 }, "image": "https://osswald.ch/cdn/shop/files/baccarat_rouge_extrait_de_parfum_70ml.jpg?v=1764945479", "description": "Saffron and jasmine with ambergris" },
  { "id": 11, "name": "Tom Ford Black Orchid", "category": "premium", "price": { "10g": 110000, "50g": 420000, "100g": 780000 }, "image": "https://cdn.aromo.ru/upload/resize_cache/iblock/89c/450_450_040cd750bba9870f18aada2478b24840a/tom-ford-black-orchid-hair-mist-2017-female-2292127.jpg", "description": "Dark orchid and spice with vanilla" },
  { "id": 12, "name": "Tom Ford Oud Wood", "category": "premium", "price": { "10g": 110000, "50g": 420000, "100g": 780000 }, "image": "https://elisium.uz/thumb/2/J7Z8ogILglcZt8m1E_pM2g/r/d/c36707f4-e754-4b15-be67-d179cf8f6525-min.png", "description": "Rare oud with rosewood and cardamom" },
  { "id": 13, "name": "Tom Ford Tobacco Vanille", "category": "premium", "price": { "10g": 115000, "50g": 435000, "100g": 800000 }, "image": "https://parfumstock.uz/thumb/2/ynjVcVl2n_RRwXWBPZlUMA/r/d/23829898005-1.jpg", "description": "Tobacco leaf and vanilla with cacao" },
  { "id": 14, "name": "Tom Ford Lost Cherry", "category": "premium", "price": { "10g": 150000, "50g": 570000, "100g": 1050000 }, "image": "https://ir.ozone.ru/s3/multimedia-8/c1000/6843402908.jpg", "description": "Black cherry and almond with Turkish rose" },
  { "id": 15, "name": "Tom Ford Ombre Leather", "category": "premium", "price": { "10g": 140000, "50g": 530000, "100g": 980000 }, "image": "https://dutyfree.uz/thumb/2/f0fpd8nnC_lKRFRXkapjpA/r/d/8_16.jpg", "description": "Leather and cardamom with patchouli" },
  { "id": 16, "name": "Yves Saint Laurent Black Opium", "category": "bestseller", "price": { "10g": 92000, "50g": 350000, "100g": 650000 }, "image": "https://cdn.bloombeauty.uz/products/cc3efb36b5365dc29bb3556982f38dff.jpeg", "description": "Coffee and vanilla with white flowers" },
  { "id": 17, "name": "Yves Saint Laurent Libre", "category": "bestseller", "price": { "10g": 95000, "50g": 360000, "100g": 670000 }, "image": "https://perfumer.uz/image/cache/catalog/product/YSL%20LIBRE%20EDP%202-1000x1000.jpg", "description": "Lavender and orange blossom fusion" },
  { "id": 18, "name": "Yves Saint Laurent Y", "category": "bestseller", "price": { "10g": 88000, "50g": 330000, "100g": 610000 }, "image": "https://olcha.uz/image/700x700/products/cdn_1/supplier/stores/1/2025-02-11/g4iIcMq31n5f6Mb4ye77zgIY6Vg3VlwrAL8BhaXMAtPP04nHPJhj9mfqNTfk.jpg", "description": "Fresh and woody with bergamot and sage" },
  { "id": 19, "name": "Yves Saint Laurent La Nuit", "category": "bestseller", "price": { "10g": 92000, "50g": 350000, "100g": 650000 }, "image": "https://elcos.uz/static/siteApp/media/yves-saint-laurent_la-nuit-de-l-homme-le-parfum_man.jpg", "description": "Spicy and woody with cardamom and cedar" },
  { "id": 20, "name": "Yves Saint Laurent Kouros", "category": "budget", "price": { "10g": 85000, "50g": 320000, "100g": 590000 }, "image": "https://elisium.uz/thumb/2/USoBCIWtT1bgCVftr6aPuQ/r/d/kouros-1.jpg", "description": "Aromatic fougere with clove and oakmoss" },
  { "id": 21, "name": "Versace Eros", "category": "bestseller", "price": { "10g": 78000, "50g": 295000, "100g": 545000 }, "image": "https://i.makeupstore.uz/6/6f/6fkecjtnaxkb.jpg", "description": "Mint leaves and Italian lemon zest" },
  { "id": 22, "name": "Versace Dylan Blue", "category": "bestseller", "price": { "10g": 85000, "50g": 320000, "100g": 590000 }, "image": "https://i.makeupstore.uz/k/kj/kjxhuxu7uau1.jpg", "description": "Aquatic woody with fig and black pepper" },
  { "id": 23, "name": "Versace Bright Crystal", "category": "bestseller", "price": { "10g": 78000, "50g": 295000, "100g": 545000 }, "image": "https://cdn.bloombeauty.uz/products/63181748847971.webp", "description": "Pomegranate and yuzu with peony" },
  { "id": 24, "name": "Versace Pour Homme", "category": "budget", "price": { "10g": 82000, "50g": 310000, "100g": 570000 }, "image": "https://i.makeupstore.uz/k/kj/kjxhuxu7uau1.jpg", "description": "Fresh citrus with neroli and bergamot" },
  { "id": 25, "name": "Armani Code", "category": "bestseller", "price": { "10g": 82000, "50g": 310000, "100g": 570000 }, "image": "https://parfumgallery.uz/_next/image?url=https%3A%2F%2Fspaces.parfumgallery.uz%2Fimages%2Fproducts%2F2026-01-28T08-17-10-406Z_Frame%20520588.png&w=1080&q=100", "description": "Citrus and woody with olive tree blossom" },
  { "id": 26, "name": "Giorgio Armani Si", "category": "bestseller", "price": { "10g": 90000, "50g": 340000, "100g": 630000 }, "image": "https://elisium.uz/thumb/2/LN4AsbhhXhayzGWMpoIzaw/750r750/d/giorgio-armani-si-edp-100-ml-1561374916-min.png", "description": "Modern chypre with blackcurrant nectar" },
  { "id": 27, "name": "Acqua di Gio", "category": "bestseller", "price": { "10g": 85000, "50g": 320000, "100g": 590000 }, "image": "https://s3.fortifai.uz/shop/moderation/partner-1077/1732949216-frrdcdkhgjth.jpg", "description": "Aquatic fresh with bergamot and jasmine" },
  { "id": 28, "name": "Acqua di Gio Profondo", "category": "bestseller", "price": { "10g": 90000, "50g": 340000, "100g": 630000 }, "image": "https://m.media-amazon.com/images/I/71jMzRavmSL._SL1500_.jpg", "description": "Deep aquatic with green mandarin and bergamot" },
  { "id": 29, "name": "Hugo Boss Bottled", "category": "budget", "price": { "10g": 75000, "50g": 280000, "100g": 520000 }, "image": "https://elisium.uz/thumb/2/unAU75zNIHfXQ7Dl90w8Fw/r/d/hugo-boss-mens-bottled-parfum-338-oz-fragrances-3616303173098_1.jpg", "description": "Apple and cinnamon with woody notes" },
  { "id": 30, "name": "Hugo Boss The Scent", "category": "budget", "price": { "10g": 82000, "50g": 310000, "100g": 570000 }, "image": "https://encrypted-tbn0.gstatic.com/images?q=tbn:ANd9GcS4RCANo-oSScmgfFCyMFkx9Cu1yg_psk7rQg&s", "description": "Ginger and maninka with leather" },
  { "id": 31, "name": "Dolce & Gabbana The One", "category": "bestseller", "price": { "10g": 89000, "50g": 335000, "100g": 620000 }, "image": "https://parfumgallery.uz/_next/image?url=https%3A%2F%2Fspaces.parfumgallery.uz%2Fimages%2Fproducts%2F2026-01-13T11-13-41-264Z_Frame%20520576.png&w=1080&q=100", "description": "Ginger and tobacco with amber" },
  { "id": 32, "name": "Dolce & Gabbana Light Blue", "category": "bestseller", "price": { "10g": 82000, "50g": 310000, "100g": 570000 }, "image": "https://parfumgallery.uz/_next/image?url=https%3A%2F%2Fspaces.parfumgallery.uz%2Fimages%2Fproducts%2F2025-10-30T07-23-53-970Z_DG_FF_NEW_LB_EDT_30ML_8057971188178_LINEUP_ERETAIL_COMBO_JPEG_2000X2000_NO_REFL__17.jpg&w=1080&q=100", "description": "Sicilian lemon and cedar with rose" },
  { "id": 33, "name": "Paco Rabanne 1 Million", "category": "bestseller", "price": { "10g": 82000, "50g": 310000, "100g": 570000 }, "image": "https://parfumgallery.uz/_next/image?url=https%3A%2F%2Fspaces.parfumgallery.uz%2Fimages%2Fproducts%2F2023-07-28T12-20-00-153Z_3349668579839.png&w=1080&q=100", "description": "Spicy leather with grapefruit and mint" },
  { "id": 34, "name": "Paco Rabanne Invictus", "category": "budget", "price": { "10g": 81000, "50g": 305000, "100g": 565000 }, "image": "https://i.letu.ru/common/img/pim/2025/01/EX_a1f097a2-a681-40b3-8af6-9679d510ce67.jpg", "description": "Grapefruit and bay leaf with marine accord" },
  { "id": 35, "name": "Paco Rabanne Lady Million", "category": "bestseller", "price": { "10g": 85000, "50g": 320000, "100g": 590000 }, "image": "https://parfumgallery.uz/_next/image?url=https%3A%2F%2Fspaces.parfumgallery.uz%2Fimages%2Fproducts%2F2025-09-11T12-44-18-015Z_AUX_bc15a904-eb87-4096-8a22-e5a9365793fd.webp&w=1080&q=100", "description": "Honey and raspberry with jasmine" },
  { "id": 36, "name": "Prada Luna Rossa", "category": "budget", "price": { "10g": 86000, "50g": 325000, "100g": 600000 }, "image": "https://parfumgallery.uz/_next/image?url=https%3A%2F%2Fspaces.parfumgallery.uz%2Fimages%2Fproducts%2F2025-12-25T08-46-02-320Z_prada_luna_rossa_edp_still_trio_ingredients_with_packshot_1x1_dmi.png&w=1080&q=100", "description": "Metallic lavender and green notes" },
  { "id": 37, "name": "Prada L'Homme", "category": "budget", "price": { "10g": 87000, "50g": 330000, "100g": 610000 }, "image": "https://parfumgallery.uz/_next/image?url=https%3A%2F%2Fspaces.parfumgallery.uz%2Fimages%2Fproducts%2F2025-12-24T10-35-14-165Z_Frame%20520578.png&w=1080&q=100", "description": "Iris and amber with clean soapy notes" },
  { "id": 38, "name": "Burberry Her", "category": "bestseller", "price": { "10g": 84000, "50g": 315000, "100g": 585000 }, "image": "https://parfumgallery.uz/_next/image?url=https%3A%2F%2Fspaces.parfumgallery.uz%2Fimages%2Fproducts%2F2022-11-30T12-10-19-374Z_26b9bf66cf6e4a46a6046a2bd188b089TsO524jUAPCQt1Ry-0.jpg&w=1080&q=100", "description": "Berries and jasmine with musk" },
  { "id": 39, "name": "Burberry London", "category": "budget", "price": { "10g": 88000, "50g": 330000, "100g": 610000 }, "image": "https://i.makeupstore.uz/w/wm/wm3pg1rabyjf.jpg", "description": "Cinnamon and tobacco with woody notes" },
  { "id": 40, "name": "Burberry Touch", "category": "budget", "price": { "10g": 84000, "50g": 315000, "100g": 585000 }, "image": "https://i.makeupstore.uz/j/jo/jov34nvrvzzq.jpg", "description": "Violet and musk with white pepper" },
  { "id": 41, "name": "Calvin Klein One", "category": "budget", "price": { "10g": 72000, "50g": 270000, "100g": 500000 }, "image": "https://parfumgallery.uz/_next/image?url=https%3A%2F%2Fspaces.parfumgallery.uz%2Fimages%2Fproducts%2F2025-05-19T07-16-44-794Z_CAK_CKONE_ESS_25_EDP_200ml_pack_Angle.psd-JPG-300dpi-2000px.jpeg&w=1080&q=100", "description": "Citrus and green notes for all" },
  { "id": 42, "name": "Calvin Klein Euphoria", "category": "budget", "price": { "10g": 83000, "50g": 310000, "100g": 575000 }, "image": "https://i.makeupstore.uz/l/lp/lptwiro4jbz0.jpg", "description": "Pomegranate and orchid with amber" },
  { "id": 43, "name": "Davidoff Cool Water", "category": "budget", "price": { "10g": 68000, "50g": 255000, "100g": 475000 }, "image": "https://elisium.uz/thumb/2/OpAvqCvE4CnP2j-njntGuA/r/d/davidoff-cool-water-eau-de-toilette-125ml.jpg", "description": "Fresh aquatic with mint and lavender" },
  { "id": 44, "name": "Mont Blanc Explorer", "category": "budget", "price": { "10g": 82000, "50g": 310000, "100g": 570000 }, "image": "https://perfumer.uz/image/cache/catalog/%D0%94%D0%BB%D1%8F%20%D0%BC%D1%83%D0%B6%D0%B8%D0%BD%202024/mont%20blanc%20exlorer%202024%20-%202-1000x1000.jpg", "description": "Vetiver and patchouli with bergamot" },
  { "id": 45, "name": "Mont Blanc Legend", "category": "budget", "price": { "10g": 76000, "50g": 285000, "100g": 530000 }, "image": "https://i.makeupstore.uz/p/pt/ptghuysnnpmt.jpg", "description": "Oakmoss and apple with tonka bean" },
  { "id": 46, "name": "Azzaro Wanted", "category": "budget", "price": { "10g": 79000, "50g": 300000, "100g": 560000 }, "image": "https://i.makeupstore.uz/o/os/osjuaezvkjw5.jpg", "description": "Cardamom and tonka bean with lemon" },
  { "id": 47, "name": "Azzaro Chrome", "category": "budget", "price": { "10g": 75000, "50g": 280000, "100g": 520000 }, "image": "https://i.makeupstore.uz/8/8q/8q1bjuaomcwp.jpg", "description": "Fresh citrus with metallic notes" },
  { "id": 48, "name": "Lacoste Blanc", "category": "budget", "price": { "10g": 78000, "50g": 295000, "100g": 545000 }, "image": "https://encrypted-tbn0.gstatic.com/images?q=tbn:ANd9GcTJttUWPMuQszXPbslkVu3v_jnb-3IiVVVwaQ&s", "description": "Grapefruit and rosemary with cedar" },
  { "id": 49, "name": "Lacoste Essential", "category": "budget", "price": { "10g": 76000, "50g": 285000, "100g": 530000 }, "image": "https://parfumstock.uz/thumb/2/hSab_Ff4vwVGVFaLy2uWog/r/d/parfum_lacost.jpg", "description": "Tomato leaf and citrus with woody notes" },
  { "id": 50, "name": "Lacoste L.12.12", "category": "budget", "price": { "10g": 80000, "50g": 300000, "100g": 560000 }, "image": "https://i.letu.ru/common/img/pim/2025/01/AUX_4338e6d9-a158-4ff9-a20d-32d99e0a5531.jpg", "description": "Clean and fresh with white notes" },
  { "id": 51, "name": "Jean Paul Gaultier Le Male", "category": "budget", "price": { "10g": 84000, "50g": 315000, "100g": 585000 }, "image": "https://parfumstock.uz/thumb/2/tAED9HEBlXaUY1yRA5Mp3Q/r/d/13827.jpg", "description": "Mint and lavender with vanilla" },
  { "id": 52, "name": "Jean Paul Gaultier Ultra Male", "category": "budget", "price": { "10g": 86000, "50g": 325000, "100g": 600000 }, "image": "https://parfumstock.uz/thumb/2/FA6K8TMgagGRWGm2vGOSRQ/r/d/7036595_a1.jpg", "description": "Pear and vanilla with black lavender" },
  { "id": 53, "name": "Jean Paul Gaultier Scandal", "category": "bestseller", "price": { "10g": 92000, "50g": 350000, "100g": 650000 }, "image": "https://parfumgallery.uz/_next/image?url=https%3A%2F%2Fspaces.parfumgallery.uz%2Fimages%2Fproducts%2F2023-01-12T10-25-03-962Z_SJP-22902_65154953_JPG-SC-PH-EDT-50-ML.webp&w=1080&q=100", "description": "Caramel and gardenia with patchouli" },
  { "id": 54, "name": "Carolina Herrera Good Girl", "category": "bestseller", "price": { "10g": 95000, "50g": 360000, "100g": 670000 }, "image": "https://www.letoile.uz/common/img/pim/2025/05/AUX_bb3867d3-eff3-426b-a93b-5a3f5d969866.jpg", "description": "Tuberose and tonka with cocoa" },
  { "id": 55, "name": "Carolina Herrera 212 VIP", "category": "bestseller", "price": { "10g": 90000, "50g": 340000, "100g": 630000 }, "image": "https://encrypted-tbn0.gstatic.com/images?q=tbn:ANd9GcT_kAokwnaZ8rTNC0RvS2_k9WEjR3LoRy5QtA&s", "description": "Passion fruit and rum with vanilla" },
  { "id": 56, "name": "Carolina Herrera Bad Boy", "category": "budget", "price": { "10g": 90000, "50g": 340000, "100g": 630000 }, "image": "https://parfumgallery.uz/_next/image?url=https%3A%2F%2Fspaces.parfumgallery.uz%2Fimages%2Fproducts%2F2025-09-12T11-27-05-104Z_SCH-39948_65198208_BAD-BOY-COBALT-ELIXIR-100-ML.png&w=1080&q=100", "description": "Black pepper and tonka with cedar" },
  { "id": 57, "name": "Bvlgari Aqva", "category": "budget", "price": { "10g": 82000, "50g": 310000, "100g": 570000 }, "image": "https://parfumgallery.uz/_next/image?url=https%3A%2F%2Fspaces.parfumgallery.uz%2Fimages%2Fproducts%2F2023-04-28T12-35-21-513Z_2%20(5).jfif&w=1080&q=100", "description": "Aquatic with mandarin and posidonia" },
  { "id": 58, "name": "Bvlgari Man in Black", "category": "budget", "price": { "10g": 95000, "50g": 360000, "100g": 670000 }, "image": "https://parfumstock.uz/d/man-in-black-parfum-by-bvlgari.webp", "description": "Leather and rum with spices" },
  { "id": 59, "name": "Bvlgari Omnia", "category": "budget", "price": { "10g": 88000, "50g": 330000, "100g": 610000 }, "image": "https://lifestyleperfume.am/images/product/1010/1602603768-Bvlgari-Omnia-Crystalline-EDT-65ml-2.jpg", "description": "White flowers and spices with wood" },
  { "id": 60, "name": "Bvlgari Tygar style", "category": "budget", "price": { "10g": 92000, "50g": 350000, "100g": 650000 }, "image": "https://encrypted-tbn0.gstatic.com/images?q=tbn:ANd9GcRIyTtETcJTRcV7H8EvL5q2qtROb9TSK9YxOw&s", "description": "Grapefruit and cyclamen with vetiver" },
  { "id": 61, "name": "Montale Intense Cafe", "category": "arab", "price": { "10g": 95000, "50g": 360000, "100g": 670000 }, "image": "https://elisium.uz/thumb/2/juEm5Ch2IEmPIQ34dCax1Q/r/d/1647437566_intensecafe-3244-7425x7425-art-scale-2_00x.jpg", "description": "Coffee and rose with amber and vanilla" },
  { "id": 62, "name": "Montale Roses Musk", "category": "arab", "price": { "10g": 95000, "50g": 360000, "100g": 670000 }, "image": "https://elisium.uz/thumb/2/VEAPlYlq8p5QEYSMXCP11A/r/d/kvepalai-montale-roses-musk-intense-1.jpg", "description": "Rose and jasmine with musk" },
  { "id": 63, "name": "Montale Arabians Tonka", "category": "arab", "price": { "10g": 98000, "50g": 370000, "100g": 690000 }, "image": "https://olcha.uz/image/700x700/products/cdn_1/supplier/stores/1/2024-03-13/7bbgOjG1j12LPGZa2RPjimHbzPvRTAQP389mQhR4HiHnrb0d9ojZBxgMruvM.jpg", "description": "Tonka and oud with praline" },
  { "id": 64, "name": "Montale Chocolate Greedy", "category": "arab", "price": { "10g": 95000, "50g": 360000, "100g": 670000 }, "image": "https://www.myperfumeshop.qa/cdn/shop/products/montale-chocolate-greedy-edp-perfume-cologne-522531.png?v=1703356062&width=2048", "description": "Chocolate and orange with vanilla" },
  { "id": 65, "name": "Mancera Cedrat Boise", "category": "arab", "price": { "10g": 98000, "50g": 370000, "100g": 690000 }, "image": "https://perfumer.uz/image/cache/catalog/%D0%A3%D0%BD%D0%B8%D1%81%D0%B5%D0%BA%D1%81%202024/Mancera%20Cedrat%20Boise%20(1)-1000x1000.jpg", "description": "Citrus and woody with leather" },
  { "id": 66, "name": "Mancera Red Tobacco", "category": "arab", "price": { "10g": 98000, "50g": 370000, "100g": 690000 }, "image": "https://perfumer.uz/image/cache/catalog/%D0%A3%D0%BD%D0%B8%D1%81%D0%B5%D0%BA%D1%81%202024/Mancera%20Red%20Tobacco%20Intense-1000x1000.jpg", "description": "Tobacco and spice with woody notes" },
  { "id": 67, "name": "Mancera Instant Crush", "category": "arab", "price": { "10g": 102000, "50g": 385000, "100g": 715000 }, "image": "https://elcos.uz/static/siteApp/media/e06bc73a-b8a3-425b-9d28-eb2fc96d1cda.jpg", "description": "Saffron and citrus with woody notes" },
  { "id": 68, "name": "Lattafa Khamrah", "category": "arab", "price": { "10g": 58000, "50g": 220000, "100g": 410000 }, "image": "https://s3.fortifai.uz/shop/moderation/partner-1274/1758963013-dfsg.PNG", "description": "Spicy and sweet with cinnamon and dates" },
  { "id": 69, "name": "Lattafa Asad", "category": "arab", "price": { "10g": 55000, "50g": 210000, "100g": 390000 }, "image": "https://encrypted-tbn0.gstatic.com/images?q=tbn:ANd9GcQFam7rLz4HbSrF1mmNXEb0aMrhW2X9c9eA0A&s", "description": "Oud and vanilla with spicy notes" },
  { "id": 70, "name": "Lattafa Yara", "category": "arab", "price": { "10g": 48000, "50g": 180000, "100g": 340000 }, "image": "https://elisium.uz/thumb/2/BufJlLxtnREUvMoXC5jx6g/750r750/d/02agiodssg_b731d78c-ac7e-4245-ae2f-9fe764522738_533x.png", "description": "Floral and fruity with caramel" },
  { "id": 71, "name": "Lattafa Oud Mood", "category": "arab", "price": { "10g": 52000, "50g": 195000, "100g": 365000 }, "image": "https://princesscosmeticsqa.com/cdn/shop/files/IMG-6708.jpg?v=1752499352", "description": "Oud and rose with amber" },
  { "id": 72, "name": "Rasasi Hawas", "category": "arab", "price": { "10g": 48000, "50g": 180000, "100g": 340000 }, "image": "https://encrypted-tbn0.gstatic.com/images?q=tbn:ANd9GcQG5sded-q8zaUSESwPV_ni46EvgNHfA43fxQ&s", "description": "Fresh aquatic with citrus and musk" },
  { "id": 73, "name": "Ajmal Amber Wood", "category": "arab", "price": { "10g": 58000, "50g": 220000, "100g": 410000 }, "image": "https://encrypted-tbn0.gstatic.com/images?q=tbn:ANd9GcStjoo9C1NwcAnRKZZHPEV6Y5kiV8XwZYMsfQ&s", "description": "Amber and woody with spices" },
  { "id": 74, "name": "Al Haramain Amber Oud", "category": "arab", "price": { "10g": 55000, "50g": 210000, "100g": 390000 }, "image": "https://s3.fortifai.uz/shop/moderation/partner-1279/1743055467-1.png", "description": "Amber and oud with vanilla" },
  { "id": 75, "name": "Swiss Arabian Shaghaf Oud", "category": "arab", "price": { "10g": 62000, "50g": 235000, "100g": 435000 }, "image": "https://i.makeupstore.uz/8/8m/8mluh31n2slo.jpg", "description": "Oud and rose with spices" },
  { "id": 76, "name": "Arabian Oud Kalemat", "category": "arab", "price": { "10g": 58000, "50g": 220000, "100g": 410000 }, "image": "https://ir.ozone.ru/s3/multimedia-j/6428098627.jpg", "description": "Oud and musk with floral notes" },
  { "id": 77, "name": "Arabian Oud Woody", "category": "arab", "price": { "10g": 55000, "50g": 210000, "100g": 390000 }, "image": "https://cdn.salla.sa/doPqe/3bee9adf-3c1a-42fa-b206-c1b6c702d096-1000x1000-vCSFZ2DjxWv47tSbLYKcqDDtXPp4SJCKlReu4vVU.png", "description": "Woody and oud with amber" },
  { "id": 78, "name": "Initio Oud for Greatness", "category": "premium", "price": { "10g": 145000, "50g": 550000, "100g": 1020000 }, "image": "https://i.makeupstore.uz/d/dq/dqpfzra6oj5h.jpg", "description": "Oud and saffron with musk" },
  { "id": 79, "name": "Initio Side Effect", "category": "premium", "price": { "10g": 135000, "50g": 510000, "100g": 945000 }, "image": "Initio Side Effect", "description": "Rum and tobacco with vanilla" },
  { "id": 80, "name": "Initio Rehab", "category": "premium", "price": { "10g": 118000, "50g": 445000, "100g": 825000 }, "image": "https://elisium.uz/d/3701415901452-alt1_1800x1800.webp", "description": "Thyme and rose with lavender" },
  { "id": 81, "name": "Xerjoff Naxos", "category": "premium", "price": { "10g": 115000, "50g": 435000, "100g": 800000 }, "image": "https://encrypted-tbn0.gstatic.com/images?q=tbn:ANd9GcRwvVv43ObGP6nmygPkPke3IXhKayfzx2ClLA&s", "description": "Honey and lavender with tobacco" },
  { "id": 82, "name": "Xerjoff Erba Pura", "category": "premium", "price": { "10g": 112000, "50g": 425000, "100g": 785000 }, "image": "https://encrypted-tbn0.gstatic.com/images?q=tbn:ANd9GcT0SLVvvPLgfJEs3xzWviu3a5dtycyV0p-MzQ&s", "description": "Sicilian lemon and pineapple with white musk" },
  { "id": 83, "name": "Xerjoff Alexandria II", "category": "premium", "price": { "10g": 175000, "50g": 665000, "100g": 1230000 }, "image": "https://elcos.uz/static/siteApp/media/66170_1726411168_Xerjoff_Alexandria_II_Anniversary.jpg", "description": "Laotian oud and rose with sandalwood" },
  { "id": 84, "name": "Nishane Hacivat", "category": "premium", "price": { "10g": 155000, "50g": 590000, "100g": 1090000 }, "image": "https://elisium.uz/thumb/2/PxZPS89z63AcyBmST7C8mQ/r/d/15484725_30137631_2048-art-scale-2_00x.jpg", "description": "Pineapple and bergamot with oakmoss" },
  { "id": 85, "name": "Nishane Ani", "category": "premium", "price": { "10g": 160000, "50g": 605000, "100g": 1120000 }, "image": "https://encrypted-tbn0.gstatic.com/images?q=tbn:ANd9GcT9awyhDiDIQWna4dBWXE-PghpTk3vMvnjkGA&s", "description": "Vanilla and blackcurrant with ginger" },
  { "id": 86, "name": "Amouage Interlude", "category": "premium", "price": { "10g": 155000, "50g": 590000, "100g": 1090000 }, "image": "https://encrypted-tbn0.gstatic.com/images?q=tbn:ANd9GcQFZmAFPN7GQkHcRZ_I6Fd2dVZBHfZ6tIytHg&s", "description": "Oud and frankincense with amber" },
  { "id": 87, "name": "Amouage Reflection Man", "category": "premium", "price": { "10g": 145000, "50g": 550000, "100g": 1020000 }, "image": "https://perfumer.uz/image/cache/catalog/M%20Product/Amouage%20Reflection%20Man%203-1000x1000.jpg", "description": "Iris and violet with sandalwood" },
  { "id": 88, "name": "Kilian Angels' Share", "category": "premium", "price": { "10g": 160000, "50g": 605000, "100g": 1120000 }, "image": "https://cdn.fragrancenet.com/images/photos/1600x1600/461449.jpg", "description": "Cognac and oak with cinnamon" },
  { "id": 89, "name": "Kilian Black Phantom", "category": "premium", "price": { "10g": 165000, "50g": 625000, "100g": 1150000 }, "image": "https://m.media-amazon.com/images/I/71Vyjtw637L.jpg", "description": "Coffee and rum with dark chocolate" },
  { "id": 90, "name": "Kilian Love Don't Be Shy", "category": "premium", "price": { "10g": 170000, "50g": 645000, "100g": 1190000 }, "image": "https://ir.ozone.ru/s3/multimedia-1-y/7274888530.jpg", "description": "Rose and neroli with marshmallow" },
  { "id": 91, "name": "Maison Francis Kurkdjian Baccarat Rouge style", "category": "premium", "price": { "10g": 150000, "50g": 570000, "100g": 1050000 }, "image": "https://www.smallflower.com/cdn/shop/products/Untitleddesign_51_-min_ede10575-3d9d-4271-b1cc-89a1df2ace9b.png?v=1773957334&width=1946", "description": "Saffron and jasmine with ambergris" },
  { "id": 92, "name": "Byredo Gypsy Water", "category": "premium", "price": { "10g": 105000, "50g": 400000, "100g": 740000 }, "image": "https://parfumstock.uz/thumb/2/PJhXByk3lwGivR_qxIQhiQ/r/d/methode_times_prod_web_bin_6d0eeb14-21b3-11ea-bf0a-65463b7bd0d0-min_2.jpg", "description": "Bergamot and juniper with incense" },
  { "id": 93, "name": "Byredo Bal d'Afrique", "category": "premium", "price": { "10g": 108000, "50g": 410000, "100g": 760000 }, "image": "https://www.myperfumeshop.com.au/cdn/shop/articles/bal-dafrique-review-one-of-the-best-byredo-perfumes-834611.jpg?v=1724245625&width=2048", "description": "Jasmine and violet with neroli" },
  { "id": 94, "name": "Byredo Mojave Ghost", "category": "premium", "price": { "10g": 110000, "50g": 420000, "100g": 780000 }, "image": "https://parfumstock.uz/thumb/2/Fy677dW6oFv7fjC4V_Cz0Q/r/d/1-62f899a0879d7301dd876ba6d8b5ceca-4416445962bc6629b9adb2fbf40e5662.jpg", "description": "Ambrette and sandalwood with musk" },
  { "id": 95, "name": "Le Labo Santal 33", "category": "premium", "price": { "10g": 125000, "50g": 475000, "100g": 880000 }, "image": "https://parfumstock.uz/thumb/2/CGZ355MpC2uw67C-AzZ0zg/r/d/42367294_x1_kk.jpg", "description": "Sandalwood and cedar with cardamom" },
  { "id": 96, "name": "Le Labo Another 13", "category": "premium", "price": { "10g": 135000, "50g": 510000, "100g": 945000 }, "image": "https://parfumstock.uz/thumb/2/NEPux0_JzsE7aJ61iPvnxQ/r/d/13319643-1775156151602439.jpg", "description": "Ambroxan and moss with musk" },
  { "id": 97, "name": "Maison Margiela Jazz Club", "category": "premium", "price": { "10g": 95000, "50g": 360000, "100g": 670000 }, "image": "https://elisium.uz/thumb/2/EZ8LjO-n4XSbShxCGCqZmQ/r/d/13183501-1754898460059445-art-scale-2_00x.jpg", "description": "Rum and tobacco with vanilla" },
  { "id": 98, "name": "Maison Margiela By the Fireplace", "category": "premium", "price": { "10g": 98000, "50g": 370000, "100g": 690000 }, "image": "https://cdn.bloombeauty.uz/products/03c4187dc24ff1bc7f005a97251363b8.jpeg", "description": "Chestnut and vanilla with clove" },
  { "id": 99, "name": "Maison Margiela Lazy Sunday", "category": "premium", "price": { "10g": 92000, "50g": 350000, "100g": 650000 }, "image": "https://encrypted-tbn0.gstatic.com/images?q=tbn:ANd9GcQJ9de66J0jz5xhSRzB9rnhTa533I7-Wtx_mw&s", "description": "Lily and iris with white musk" },
  { "id": 100, "name": "Jo Malone Wood Sage & Sea Salt", "category": "premium", "price": { "10g": 115000, "50g": 435000, "100g": 800000 }, "image": "https://parfumstock.uz/thumb/2/7Ac8GPF1p7JCNehHm1v9-w/r/d/jo_sku_l41501_1000x1000_0-1800x1800.jpg", "description": "Sage and sea salt with ambrette" },
  { "id": 101, "name": "Jo Malone Blackberry & Bay", "category": "premium", "price": { "10g": 110000, "50g": 420000, "100g": 780000 }, "image": "https://parfumstock.uz/thumb/2/FT7xrF6Xji6ByncNDkaIWA/r/d/1485237-jo-malone-london-blackberry-bay-cologne-100-mlfa77ed25.jpg", "description": "Blackberry and bay with cedar" },
  { "id": 102, "name": "Gucci Guilty", "category": "bestseller", "price": { "10g": 88000, "50g": 330000, "100g": 610000 }, "image": "https://encrypted-tbn0.gstatic.com/images?q=tbn:ANd9GcQKsQS3vecHlVUXSd26eRepPrJzSlxWtKHw7Q&s", "description": "Lavender and patchouli with orange blossom" },
  { "id": 103, "name": "Gucci Bloom", "category": "bestseller", "price": { "10g": 95000, "50g": 360000, "100g": 670000 }, "image": "https://encrypted-tbn0.gstatic.com/images?q=tbn:ANd9GcSztkDYg1hv1adcPj7MCIqd-I0pJD_rVJqPXw&s", "description": "Tuberose and jasmine with honeysuckle" },
  { "id": 104, "name": "Givenchy Gentleman", "category": "bestseller", "price": { "10g": 92000, "50g": 350000, "100g": 650000 }, "image": "https://www.givenchybeauty.com/dw/image/v2/BBZW_PRD/on/demandware.static/-/Sites-givenchy-beauty-master/default/dwe91115c6/images/P011161/3274872439078_P011161_GENTLEMAN-22-EDP-RP-100ML_4.png?sw=1200&sh=1200&strip=false", "description": "Iris and cedar with vetiver" }
]
